db_psycopg2
