Metadata-Version: 1.1
Name: db-psycopg2
Version: 0.0.6
Summary: psycopg2 driver for db
Home-page: https://github.com/lgastako/db-psycopg2
Author: John Evans
Author-email: lgastako@gmail.com
License: UNKNOWN
Platform: UNKNOWN
Provides: db_psycopg2
